LICENCE
README.md
pyproject.toml
poisson_transform.egg-info/PKG-INFO
poisson_transform.egg-info/SOURCES.txt
poisson_transform.egg-info/dependency_links.txt
poisson_transform.egg-info/top_level.txt
src/__init__.py
src/poisson_2D_transform.py