Metadata-Version: 2.1
Name: poisson_transform
Version: 0.2.2
Summary: Poisson Solver in Tranformed 2D Space using Finite Difference
Author: Ar-Kareem
Maintainer: Ar-Kareem
Project-URL: Homepage, https://github.com/Ar-Kareem/poisson_transform/
Project-URL: Repository, https://github.com/Ar-Kareem/poisson_transform/
Project-URL: Issues, https://github.com/Ar-Kareem/poisson_transform/issues
Keywords: poisson,solver,finite difference,transformed space,2D,numerical,mathematics,physics,engineering,computational,science,research
Classifier: Development Status :: 4 - Beta
Classifier: Intended Audience :: Developers
Classifier: Intended Audience :: Education
Classifier: Intended Audience :: Science/Research
Classifier: License :: OSI Approved :: MIT License
Classifier: Programming Language :: Python :: 3.9
Classifier: Programming Language :: Python :: 3.10
Classifier: Programming Language :: Python :: 3.11
Classifier: Programming Language :: Python :: 3.12
Requires-Python: >=3.9.0
License-File: LICENCE
